pnap_network_api/__init__.py
pnap_network_api/api_client.py
pnap_network_api/api_response.py
pnap_network_api/configuration.py
pnap_network_api/exceptions.py
pnap_network_api/py.typed
pnap_network_api/rest.py
pnap_network_api/version.py
pnap_network_api/api/__init__.py
pnap_network_api/api/bgp_peer_groups_api.py
pnap_network_api/api/private_networks_api.py
pnap_network_api/api/public_networks_api.py
pnap_network_api/models/__init__.py
pnap_network_api/models/asn_details.py
pnap_network_api/models/bgp_ipv4_prefix.py
pnap_network_api/models/bgp_peer_group.py
pnap_network_api/models/bgp_peer_group_create.py
pnap_network_api/models/bgp_peer_group_patch.py
pnap_network_api/models/error.py
pnap_network_api/models/network_membership.py
pnap_network_api/models/private_network.py
pnap_network_api/models/private_network_create.py
pnap_network_api/models/private_network_modify.py
pnap_network_api/models/private_network_server.py
pnap_network_api/models/public_network.py
pnap_network_api/models/public_network_create.py
pnap_network_api/models/public_network_ip_block.py
pnap_network_api/models/public_network_ip_block_create.py
pnap_network_api/models/public_network_modify.py
pnap_network_api-3.0.1.dist-info/METADATA
pnap_network_api-3.0.1.dist-info/WHEEL
pnap_network_api-3.0.1.dist-info/top_level.txt
pnap_network_api-3.0.1.dist-info/RECORD
