Metadata-Version: 2.1
Name: pnap-network-api
Version: 3.0.1
Summary: Networks API
Home-page: UNKNOWN
Author: PhoenixNAP Team
Author-email: support@phoenixnap.com
License: Apache 2.0
Keywords: OpenAPI,OpenAPI-Generator,Networks API
Platform: UNKNOWN
Requires-Dist: urllib3 <2.1.0,>=1.25.3
Requires-Dist: python-dateutil
Requires-Dist: pydantic >=2
Requires-Dist: typing-extensions >=4.7.1
